adls_acl/__init__.py
adls_acl/auth.py
adls_acl/cli.py
adls_acl/input_parser.py
adls_acl/logger.py
adls_acl/nodes.py
adls_acl/orchestrator.py
adls_acl/schema.yml
adls_acl-0.1.0.dist-info/LICENSE
adls_acl-0.1.0.dist-info/METADATA
adls_acl-0.1.0.dist-info/WHEEL
adls_acl-0.1.0.dist-info/entry_points.txt
adls_acl-0.1.0.dist-info/top_level.txt
adls_acl-0.1.0.dist-info/RECORD
