Metadata-Version: 2.1
Name: adls_acl
Version: 0.1.0
Summary: A small tool for managing Azure DataLake Store (ADLS) Access Control Lists (ACLs).
Home-page: https://github.com/karolusz/adls-acl
Author: Karol Luszczek
Author-email: karol.luszczek@reinsight.se
License: MIT
Classifier: Intended Audience :: Developers
Classifier: Operating System :: OS Independent
Classifier: License :: OSI Approved :: MIT License
Classifier: Programming Language :: Python
Classifier: Programming Language :: Python :: 3
Classifier: Programming Language :: Python :: 3.12
Requires-Python: >=3.12
License-File: LICENSE
Requires-Dist: yamale
Requires-Dist: azure-storage-file-datalake
Requires-Dist: azure-identity
Requires-Dist: click
Provides-Extra: dev
Requires-Dist: pytest ; extra == 'dev'
Requires-Dist: pytest-cov ; extra == 'dev'
Requires-Dist: pytest-mock ; extra == 'dev'
Requires-Dist: bumpver ; extra == 'dev'
